codeanalyze/cli.py
codeanalyze-0.5.dist-info/METADATA
codeanalyze-0.5.dist-info/WHEEL
codeanalyze-0.5.dist-info/entry_points.txt
codeanalyze-0.5.dist-info/top_level.txt
codeanalyze-0.5.dist-info/RECORD
