Metadata-Version: 2.4
Name: codeanalyze
Version: 0.5
Summary: AI 기반 코드 보안 분석기 CLI
Author: snowpie
Author-email: davin0706@gmail.com
Classifier: Programming Language :: Python :: 3
Classifier: License :: OSI Approved :: MIT License
Classifier: Operating System :: OS Independent
Requires-Python: >=3.7
Dynamic: author
Dynamic: author-email
Dynamic: classifier
Dynamic: description
Dynamic: description-content-type
Dynamic: requires-python
Dynamic: summary
